teselagen/__init__.py
teselagen/api/__init__.py
teselagen/api/build_client.py
teselagen/api/build_client_models.py
teselagen/api/client.py
teselagen/api/design_client.py
teselagen/api/discover_client.py
teselagen/api/test_client.py
teselagen/api/tests/__init__.py
teselagen/api/tests/example_file.csv
teselagen/api/tests/test_build_client.py
teselagen/api/tests/test_client.py
teselagen/api/tests/test_design_client.py
teselagen/api/tests/test_discover_client.py
teselagen/api/tests/test_multiomics/EDD_OD_WT.csv
teselagen/api/tests/test_multiomics/EDD_experiment_description_file_BE_designs.csv
teselagen/api/tests/test_multiomics/EDD_experiment_description_file_WT.csv
teselagen/api/tests/test_multiomics/EDD_external_metabolites_WT.csv
teselagen/api/tests/test_multiomics/EDD_transcriptomics_WTSM.csv
teselagen/api/tests/test_multiomics.py
teselagen/api/tests/test_test_client.py
teselagen/examples/.gitignore
teselagen/examples/CRISPR-Tool.ipynb
teselagen/examples/Multiomics.ipynb
teselagen/examples/pytested/Closing-the-DBTL-Cycle.ipynb
teselagen/examples/pytested/Hello-World-TEST-module.ipynb
teselagen/examples/pytested/Hello_World_BUILD_module.ipynb
teselagen/examples/pytested/Hello_World_DESIGN_module.ipynb
teselagen/examples/pytested/dummy_organism.fasta
teselagen/examples/requirements.txt
teselagen/examples/retrieve_assembly_report.py
teselagen/utils/__init__.py
teselagen/utils/candidates_to_design.py
teselagen/utils/configuration_helper.py
teselagen/utils/crispr.py
teselagen/utils/plot_tools.py
teselagen/utils/setup_commands.py
teselagen/utils/tests/__init__.py
teselagen/utils/tests/test_utils.py
teselagen/utils/utils.py
teselagen-0.5.0.dist-info/METADATA
teselagen-0.5.0.dist-info/WHEEL
teselagen-0.5.0.dist-info/RECORD
