Metadata-Version: 2.1
Name: teselagen
Version: 0.5.0
Summary: Teselagen Biotechnology API client
Home-page: https://github.com/TeselaGen/api-client
License: MIT
Keywords: Synthetic Biology,Teselagen,DBTL,CRISPR,DNA Assembly
Author: Your Name
Author-email: you@example.com
Requires-Python: >=3.9.6,<4.0.0
Classifier: License :: OSI Approved :: MIT License
Classifier: Programming Language :: Python :: 3
Classifier: Programming Language :: Python :: 3.10
Classifier: Programming Language :: Python :: 3.11
Classifier: Programming Language :: Python :: 3.12
Requires-Dist: SecretColors (>=1.2.4,<2.0.0)
Requires-Dist: dna_features_viewer (>=3.0.3,<4.0.0)
Requires-Dist: fastaparser (>=1.1,<2.0)
Requires-Dist: openpyxl (>=3.0.7,<4.0.0)
Requires-Dist: pandas (>=2.2.3,<3.0.0)
Requires-Dist: pytest (>=6.2.5,<7.0.0)
Requires-Dist: pytest-cov (>=3.0.0,<4.0.0)
Requires-Dist: pytest-datadir (>=1.3.1,<2.0.0)
Requires-Dist: pytest-notebook (>=0.10.0,<0.11.0)
Requires-Dist: pytest-timeout (>=2.0.2,<3.0.0)
Requires-Dist: pytest-xdist (>=2.4.0,<3.0.0)
Requires-Dist: python-dotenv (>=1.0.1,<2.0.0)
Requires-Dist: requests (>=2.26.0,<3.0.0)
Requires-Dist: requests-mock (>=1.9.3,<2.0.0)
Requires-Dist: setuptools (==58.1.0)
Requires-Dist: single_version (>=1.5.1,<2.0.0)
Requires-Dist: tenacity (>=8.0.0,<9.0.0)
Requires-Dist: tqdm (>=4.62.3,<5.0.0)
Project-URL: Documentation, https://github.com/TeselaGen/api-client
Project-URL: Repository, https://github.com/TeselaGen/api-client
